tree_sitter_pymanifest/__init__.py
tree_sitter_pymanifest/py.typed
tree_sitter_pymanifest/binding.c
tree_sitter_pymanifest/__init__.pyi
tree_sitter_pymanifest/_binding.abi3.so
tree_sitter_pymanifest/queries/highlights.scm
tree_sitter_pymanifest-0.5.1.dist-info/WHEEL
tree_sitter_pymanifest-0.5.1.dist-info/LICENSE
tree_sitter_pymanifest-0.5.1.dist-info/top_level.txt
tree_sitter_pymanifest-0.5.1.dist-info/RECORD
tree_sitter_pymanifest-0.5.1.dist-info/METADATA
