Metadata-Version: 2.1
Name: tree-sitter-pymanifest
Version: 0.5.1
Summary: PyPA manifest grammar for tree-sitter
Author-email: ObserverOfTime <chronobserver@disroot.org>
License: MIT
Project-URL: Homepage, https://github.com/tree-sitter-grammars/tree-sitter-pymanifest
Project-URL: Issues, https://github.com/tree-sitter-grammars/tree-sitter-pymanifest/issues
Project-URL: Sponsor, https://github.com/sponsors/ObserverOfTime
Keywords: incremental,parsing,tree-sitter,pymanifest
Classifier: Intended Audience :: Developers
Classifier: License :: OSI Approved :: MIT License
Classifier: Topic :: Software Development :: Compilers
Classifier: Topic :: Text Processing :: Linguistic
Classifier: Typing :: Typed
Requires-Python: >=3.9
License-File: LICENSE
Provides-Extra: core
Requires-Dist: tree-sitter ~=0.22 ; extra == 'core'
